dbt/adapters/selectdb/__init__.py
dbt/adapters/selectdb/__version__.py
dbt/adapters/selectdb/column.py
dbt/adapters/selectdb/connections.py
dbt/adapters/selectdb/impl.py
dbt/adapters/selectdb/relation.py
dbt/include/selectdb/__init__.py
dbt/include/selectdb/dbt_project.yml
dbt/include/selectdb/profile_template.yml
dbt/include/selectdb/sample_profiles.yml
dbt/include/selectdb/macros/adapters/columns.sql
dbt/include/selectdb/macros/adapters/freshness.sql
dbt/include/selectdb/macros/adapters/metadata.sql
dbt/include/selectdb/macros/adapters/relation.sql
dbt/include/selectdb/macros/adapters/schema.sql
dbt/include/selectdb/macros/materializations/incremental/help.sql
dbt/include/selectdb/macros/materializations/incremental/incremental.sql
dbt/include/selectdb/macros/materializations/partition/helpers.sql
dbt/include/selectdb/macros/materializations/partition/partition.sql
dbt/include/selectdb/macros/materializations/partition/replace.sql
dbt/include/selectdb/macros/materializations/seed/helpers.sql
dbt/include/selectdb/macros/materializations/snapshot/snapshot.sql
dbt/include/selectdb/macros/materializations/snapshot/strategies.sql
dbt/include/selectdb/macros/materializations/table/create_table_as.sql
dbt/include/selectdb/macros/materializations/view/create_view_as.sql
dbt_selectdb-0.1.0.dist-info/METADATA
dbt_selectdb-0.1.0.dist-info/WHEEL
dbt_selectdb-0.1.0.dist-info/top_level.txt
dbt_selectdb-0.1.0.dist-info/RECORD
